odoo/addons/base_repair/README.rst
odoo/addons/base_repair/__init__.py
odoo/addons/base_repair/__manifest__.py
odoo/addons/base_repair/i18n/base_repair.pot
odoo/addons/base_repair/i18n/es.po
odoo/addons/base_repair/i18n/hr.po
odoo/addons/base_repair/i18n/it.po
odoo/addons/base_repair/i18n/pt_BR.po
odoo/addons/base_repair/models/__init__.py
odoo/addons/base_repair/models/repair_order.py
odoo/addons/base_repair/readme/CONTRIBUTORS.rst
odoo/addons/base_repair/readme/CREDITS.rst
odoo/addons/base_repair/readme/DESCRIPTION.rst
odoo/addons/base_repair/static/description/banner.png
odoo/addons/base_repair/static/description/icon.png
odoo/addons/base_repair/static/description/index.html
odoo/addons/base_repair/views/repair_order.xml
odoo14_addon_base_repair-14.0.1.0.1.dev14.dist-info/METADATA
odoo14_addon_base_repair-14.0.1.0.1.dev14.dist-info/WHEEL
odoo14_addon_base_repair-14.0.1.0.1.dev14.dist-info/top_level.txt
odoo14_addon_base_repair-14.0.1.0.1.dev14.dist-info/RECORD
